ovos_tts_plugin_privox/__init__.py
ovos_tts_plugin_privox/version.py
ovos_tts_plugin_privox-0.0.2.dist-info/LICENSE
ovos_tts_plugin_privox-0.0.2.dist-info/METADATA
ovos_tts_plugin_privox-0.0.2.dist-info/WHEEL
ovos_tts_plugin_privox-0.0.2.dist-info/entry_points.txt
ovos_tts_plugin_privox-0.0.2.dist-info/top_level.txt
ovos_tts_plugin_privox-0.0.2.dist-info/zip-safe
ovos_tts_plugin_privox-0.0.2.dist-info/RECORD
